src/__init__.py
src/main.py
radox-0.0.1.dist-info/METADATA
radox-0.0.1.dist-info/WHEEL
radox-0.0.1.dist-info/top_level.txt
radox-0.0.1.dist-info/RECORD
