Metadata-Version: 2.1
Name: radox
Version: 0.0.1
Summary: A WSGI based Python web framework inspired from flask
Author: Palani
Author-email: palanioffcl@gmail.com
Keywords: web,python,framework,libraries,webapps
Classifier: Development Status :: 3 - Alpha
Classifier: Environment :: Web Environment
Classifier: Programming Language :: Python :: 3.7
Classifier: Topic :: Internet :: WWW/HTTP :: WSGI :: Application
Classifier: Topic :: Internet :: WWW/HTTP
Requires-Dist: wsgi
